absfuyu/__init__.py
absfuyu/__main__.py
absfuyu/logger.py
absfuyu/py.typed
absfuyu/sort.py
absfuyu/typings.py
absfuyu/version.py
absfuyu/cli/__init__.py
absfuyu/cli/audio_group.py
absfuyu/cli/checksum_group.py
absfuyu/cli/color.py
absfuyu/cli/config_group.py
absfuyu/cli/do_group.py
absfuyu/cli/game_group.py
absfuyu/cli/tool_group.py
absfuyu/config/__init__.py
absfuyu/config/config.json
absfuyu/core/__init__.py
absfuyu/core/baseclass.py
absfuyu/core/baseclass2.py
absfuyu/core/decorator.py
absfuyu/core/docstring.py
absfuyu/core/dummy_cli.py
absfuyu/core/dummy_func.py
absfuyu/dxt/__init__.py
absfuyu/dxt/base_type.py
absfuyu/dxt/dictext.py
absfuyu/dxt/dxt_support.py
absfuyu/dxt/intext.py
absfuyu/dxt/listext.py
absfuyu/dxt/strext.py
absfuyu/extra/__init__.py
absfuyu/extra/beautiful.py
absfuyu/extra/pdf.py
absfuyu/extra/rclone.py
absfuyu/extra/xml.py
absfuyu/extra/audio/__init__.py
absfuyu/extra/audio/_util.py
absfuyu/extra/audio/convert.py
absfuyu/extra/audio/lossless.py
absfuyu/extra/da/__init__.py
absfuyu/extra/da/dadf.py
absfuyu/extra/da/dadf_base.py
absfuyu/extra/da/df_func.py
absfuyu/extra/da/export.py
absfuyu/extra/da/mplt.py
absfuyu/extra/ggapi/__init__.py
absfuyu/extra/ggapi/gdrive.py
absfuyu/extra/ggapi/glicense.py
absfuyu/extra/ggapi/glicense_df.py
absfuyu/extra/ggapi/gsheet.py
absfuyu/extra/ggapi/project.py
absfuyu/extra/img/__init__.py
absfuyu/extra/img/converter.py
absfuyu/extra/img/dup_check.py
absfuyu/extra/typst/__init__.py
absfuyu/extra/typst/compiler.py
absfuyu/fun/__init__.py
absfuyu/fun/rubik.py
absfuyu/fun/tarot.py
absfuyu/game/__init__.py
absfuyu/game/game_stat.py
absfuyu/game/schulte.py
absfuyu/game/sudoku.py
absfuyu/game/tictactoe.py
absfuyu/game/wordle.py
absfuyu/general/__init__.py
absfuyu/general/content.py
absfuyu/general/human.py
absfuyu/general/resrel.py
absfuyu/general/shape.py
absfuyu/general/tax.py
absfuyu/numbers/__init__.py
absfuyu/numbers/number_to_word.py
absfuyu/numbers/shorten_number.py
absfuyu/numbers/time_duration.py
absfuyu-6.3.0.dist-info/METADATA
absfuyu-6.3.0.dist-info/WHEEL
absfuyu-6.3.0.dist-info/entry_points.txt
absfuyu-6.3.0.dist-info/licenses/LICENSE
absfuyu-6.3.0.dist-info/RECORD
