Metadata-Version: 2.4
Name: absfuyu
Version: 6.3.0
Summary: A small collection of code
Project-URL: Homepage, https://github.com/AbsoluteWinter/absfuyu-public
Project-URL: Documentation, https://absolutewinter.github.io/absfuyu-docs/
Project-URL: Repository, https://github.com/AbsoluteWinter/absfuyu-public
Project-URL: Issues, https://github.com/AbsoluteWinter/absfuyu-public/issues
Author: somewhatcold (AbsoluteWinter)
License-Expression: MIT
License-File: LICENSE
Keywords: utilities
Classifier: Development Status :: 5 - Production/Stable
Classifier: Intended Audience :: Developers
Classifier: Intended Audience :: End Users/Desktop
Classifier: License :: OSI Approved :: MIT License
Classifier: Natural Language :: English
Classifier: Operating System :: OS Independent
Classifier: Programming Language :: Python :: 3
Classifier: Programming Language :: Python :: 3 :: Only
Classifier: Programming Language :: Python :: 3.12
Classifier: Programming Language :: Python :: 3.13
Classifier: Programming Language :: Python :: 3.14
Classifier: Topic :: Software Development :: Libraries
Classifier: Topic :: Software Development :: Libraries :: Python Modules
Classifier: Topic :: Utilities
Requires-Python: <4,>=3.12
Requires-Dist: click>=8.0.0
Requires-Dist: colorama
Provides-Extra: beautiful
Requires-Dist: rich; extra == 'beautiful'
Provides-Extra: dadf
Requires-Dist: numpy; extra == 'dadf'
Requires-Dist: openpyxl; extra == 'dadf'
Requires-Dist: pandas; extra == 'dadf'
Requires-Dist: xlsxwriter; extra == 'dadf'
Provides-Extra: docs
Requires-Dist: numpy; extra == 'docs'
Requires-Dist: pandas; extra == 'docs'
Requires-Dist: rich; extra == 'docs'
Requires-Dist: spire-pdf; extra == 'docs'
Provides-Extra: extra
Requires-Dist: numpy; extra == 'extra'
Requires-Dist: openpyxl; extra == 'extra'
Requires-Dist: pandas; extra == 'extra'
Requires-Dist: pillow; extra == 'extra'
Requires-Dist: spire-pdf; extra == 'extra'
Requires-Dist: xlsxwriter; extra == 'extra'
Requires-Dist: xmltodict; extra == 'extra'
Provides-Extra: full
Requires-Dist: bs4; extra == 'full'
Requires-Dist: defusedxml; extra == 'full'
Requires-Dist: google-api-python-client>=2.187.0; extra == 'full'
Requires-Dist: google-auth-oauthlib; extra == 'full'
Requires-Dist: google-auth>=2.45.0; extra == 'full'
Requires-Dist: imagehash; extra == 'full'
Requires-Dist: numpy; extra == 'full'
Requires-Dist: olefile; extra == 'full'
Requires-Dist: openpyxl; extra == 'full'
Requires-Dist: pandas; extra == 'full'
Requires-Dist: pillow; extra == 'full'
Requires-Dist: pillow-heif; extra == 'full'
Requires-Dist: rclone-crypt; extra == 'full'
Requires-Dist: requests; extra == 'full'
Requires-Dist: rich; extra == 'full'
Requires-Dist: spire-pdf; extra == 'full'
Requires-Dist: tqdm; extra == 'full'
Requires-Dist: typst; extra == 'full'
Requires-Dist: unidecode; extra == 'full'
Requires-Dist: xlsxwriter; extra == 'full'
Requires-Dist: xmltodict; extra == 'full'
Provides-Extra: ggapi
Requires-Dist: google-api-python-client; extra == 'ggapi'
Requires-Dist: google-auth; extra == 'ggapi'
Requires-Dist: google-auth-oauthlib; extra == 'ggapi'
Requires-Dist: requests; extra == 'ggapi'
Provides-Extra: pdf
Requires-Dist: spire-pdf; extra == 'pdf'
Provides-Extra: pic
Requires-Dist: defusedxml; extra == 'pic'
Requires-Dist: imagehash; extra == 'pic'
Requires-Dist: pillow; extra == 'pic'
Provides-Extra: rclone
Requires-Dist: rclone-crypt; extra == 'rclone'
Provides-Extra: typst
Requires-Dist: typst; extra == 'typst'
Provides-Extra: xml
Requires-Dist: xmltodict; extra == 'xml'
